pysteamupload/__main__.py
pysteamupload/generic_pysteamupload.py
pysteamupload/linux_pysteamupload.py
pysteamupload/pysteamupload_templates.py
pysteamupload/windows_pysteamupload.py
pysteamupload-0.2.0.dist-info/LICENSE
pysteamupload-0.2.0.dist-info/METADATA
pysteamupload-0.2.0.dist-info/WHEEL
pysteamupload-0.2.0.dist-info/top_level.txt
pysteamupload-0.2.0.dist-info/RECORD
